SentenceGraph/__init__.py
SentenceGraph/_modidx.py
SentenceGraph/core.py
SentenceGraph/functional.py
SentenceGraph-0.0.5.dist-info/LICENSE
SentenceGraph-0.0.5.dist-info/METADATA
SentenceGraph-0.0.5.dist-info/WHEEL
SentenceGraph-0.0.5.dist-info/entry_points.txt
SentenceGraph-0.0.5.dist-info/top_level.txt
SentenceGraph-0.0.5.dist-info/RECORD
