Metadata-Version: 2.1
Name: SentenceGraph
Version: 0.0.5
Summary: Easily create semantic graphs from text using SentenceTransformers
Home-page: https://github.com/Hevia/SentenceGraph
Author: Hevia
Author-email: anthony@hevia.dev
License: Apache Software License 2.0
Keywords: nbdev jupyter notebook python
Platform: UNKNOWN
Classifier: Development Status :: 4 - Beta
Classifier: Intended Audience :: Developers
Classifier: Natural Language :: English
Classifier: Programming Language :: Python :: 3.8
Classifier: Programming Language :: Python :: 3.9
Classifier: Programming Language :: Python :: 3.10
Classifier: License :: OSI Approved :: Apache Software License
Requires-Python: >=3.8
Requires-Dist: sentence-transformers
Requires-Dist: pandas
Provides-Extra: dev
Requires-Dist: twine ; extra == 'dev'
